kanimtool/__init__.py
kanimtool/__main__.py
kanimtool/builder.py
kanimtool/cli.py
kanimtool/inspect.py
kanimtool/io.py
kanimtool/parser.py
kanimtool-2024.11.5.dist-info/METADATA
kanimtool-2024.11.5.dist-info/WHEEL
kanimtool-2024.11.5.dist-info/entry_points.txt
kanimtool-2024.11.5.dist-info/top_level.txt
kanimtool-2024.11.5.dist-info/RECORD
