Metadata-Version: 2.1
Name: kanimtool
Version: 2024.11.5
Summary: tools to deal with kanim
Author: Aaron Tsang
Project-URL: Homepage, https://github.com/tsangwpx/kanimtool
Project-URL: Source, https://github.com/tsangwpx/kanimtool
Keywords: moding
Classifier: Development Status :: 4 - Beta
Classifier: Programming Language :: Python
Requires-Python: >=3.9
Requires-Dist: pillow >=11.0.0
Requires-Dist: numpy >=2.0.0
